utilsps/__init__.py
utilsps/files.py
utilsps-0.1.0.dist-info/METADATA
utilsps-0.1.0.dist-info/WHEEL
utilsps-0.1.0.dist-info/top_level.txt
utilsps-0.1.0.dist-info/RECORD
