Metadata-Version: 2.4
Name: utilsps
Version: 0.1.0
Summary: Simple file utilities package
Author: Your Name
Requires-Python: >=3.6
Dynamic: author
Dynamic: requires-python
Dynamic: summary
